delete_files_in_bulk/__init__.py
delete_files_in_bulk/delete_files.py
delete_files_in_bulk-0.0.2.dist-info/LICENSE
delete_files_in_bulk-0.0.2.dist-info/METADATA
delete_files_in_bulk-0.0.2.dist-info/WHEEL
delete_files_in_bulk-0.0.2.dist-info/top_level.txt
delete_files_in_bulk-0.0.2.dist-info/RECORD
