Metadata-Version: 2.1
Name: delete-files-in-bulk
Version: 0.0.2
Summary: A script for deleting files and/or directories in bulk.
Home-page: https://github.com/pypa/sampleproject
Author: M. Cheung
Author-email: xavipotter90@gmail.com
License: UNKNOWN
Project-URL: Bug Tracker, https://github.com/pypa/sampleproject/issues
Platform: UNKNOWN
Classifier: Programming Language :: Python :: 3
Classifier: License :: OSI Approved :: MIT License
Classifier: Operating System :: OS Independent
Requires-Python: >=3.6
License-File: LICENSE
